<?xml version="1.0" encoding="utf-8"?>
<fmg>
<compression>None</compression>
<version>DarkSouls3</version>
<bigendian>False</bigendian>
<entries>
<text id="1760">Можно найти возле упавших обломков</text>
<text id="11000">Временно увеличивает макс. ОЗ</text>
<text id="11001">Временно увеличивает макс. выносливость</text>
<text id="11002">Восстанавливает половину макс. ОЗ</text>
<text id="11003">Восстанавливает половину макс. ОЗ</text>
<text id="11004">Восстанавливает половину макс. ОК</text>
<text id="11005">Восстанавливает половину макс. ОК</text>
<text id="11006">Лечит недуги, повышает сопротивляемость</text>
<text id="11007">Восстанавливает ОЗ на грани смерти</text>
<text id="11008">Значительно уменьшает получаемый урон</text>
<text id="11009">Постепенно восстанавливает ОЗ</text>
<text id="11010">Временно восстанавливает выносливость</text>
<text id="11011">Временно повышает общее сопротивление</text>
<text id="11012">Временно снижает вес снаряжения</text>
<text id="11013">Временно усиливает серии атак</text>
<text id="11014">Временно усиливает заряженные атаки</text>
<text id="11015">Временно повышает эффективность переката</text>
<text id="11016">Вызывает взрыв</text>
<text id="11017">Вызывает взрыв</text>
<text id="11018">Временно повышает баланс</text>
<text id="11019">Временно сохраняет руны после смерти</text>
<text id="11020">Преобразует полученный урон в ОЗ</text>
<text id="11021">Временно увеличивает силу</text>
<text id="11022">Временно увеличивает ловкость</text>
<text id="11023">Временно увеличивает мудрость</text>
<text id="11024">Временно увеличивает веру</text>
<text id="11025">Позволяет не тратить ОК</text>
<text id="11026">Временно упрощает вывод из равновесия</text>
<text id="11027">Снимает проклятие Повелителя Крови</text>
<text id="11028">Временно увеличивает силу атак огнём</text>
<text id="11029">Временно увеличивает силу атак магией</text>
<text id="11030">Временно увеличивает силу атак молнией</text>
<text id="11031">Временно повышает мощь святых атак</text>
<text id="15000">Можно добыть, охотясь на травоядных зверей</text>
<text id="15001">%null%</text>
<text id="15002">%null%</text>
<text id="15003">%null%</text>
<text id="15004">%null%</text>
<text id="15005">%null%</text>
<text id="15006">%null%</text>
<text id="15007">%null%</text>
<text id="15008">%null%</text>
<text id="15009">%null%</text>
<text id="15010">Можно добыть, охотясь на травоядных зверей</text>
<text id="15011">%null%</text>
<text id="15012">%null%</text>
<text id="15013">%null%</text>
<text id="15014">%null%</text>
<text id="15015">%null%</text>
<text id="15016">%null%</text>
<text id="15017">%null%</text>
<text id="15018">%null%</text>
<text id="15019">%null%</text>
<text id="15020">Можно добыть, охотясь на хищных зверей</text>
<text id="15021">%null%</text>
<text id="15022">%null%</text>
<text id="15023">%null%</text>
<text id="15024">%null%</text>
<text id="15025">%null%</text>
<text id="15026">%null%</text>
<text id="15027">%null%</text>
<text id="15028">%null%</text>
<text id="15029">%null%</text>
<text id="15030">Можно добыть, охотясь на хищных зверей</text>
<text id="15031">%null%</text>
<text id="15032">%null%</text>
<text id="15033">%null%</text>
<text id="15034">%null%</text>
<text id="15035">%null%</text>
<text id="15036">%null%</text>
<text id="15037">%null%</text>
<text id="15038">%null%</text>
<text id="15039">%null%</text>
<text id="15040">Можно добыть, охотясь на хищных зверей</text>
<text id="15041">%null%</text>
<text id="15042">%null%</text>
<text id="15043">%null%</text>
<text id="15044">%null%</text>
<text id="15045">%null%</text>
<text id="15046">%null%</text>
<text id="15047">%null%</text>
<text id="15048">%null%</text>
<text id="15049">%null%</text>
<text id="15050">Можно добыть, охотясь на травоядных зверей</text>
<text id="15051">%null%</text>
<text id="15052">%null%</text>
<text id="15053">%null%</text>
<text id="15054">%null%</text>
<text id="15055">%null%</text>
<text id="15056">%null%</text>
<text id="15057">%null%</text>
<text id="15058">%null%</text>
<text id="15059">%null%</text>
<text id="15060">Можно добыть, охотясь на птиц</text>
<text id="15061">%null%</text>
<text id="15062">%null%</text>
<text id="15063">%null%</text>
<text id="15064">%null%</text>
<text id="15065">%null%</text>
<text id="15066">%null%</text>
<text id="15067">%null%</text>
<text id="15068">%null%</text>
<text id="15069">%null%</text>
<text id="15070">Иногда можно добыть во время охоты на птиц</text>
<text id="15071">%null%</text>
<text id="15072">%null%</text>
<text id="15073">%null%</text>
<text id="15074">%null%</text>
<text id="15075">%null%</text>
<text id="15076">%null%</text>
<text id="15077">%null%</text>
<text id="15078">%null%</text>
<text id="15079">%null%</text>
<text id="15080">Можно добыть, охотясь на птиц</text>
<text id="15081">%null%</text>
<text id="15082">%null%</text>
<text id="15083">%null%</text>
<text id="15084">%null%</text>
<text id="15085">%null%</text>
<text id="15086">%null%</text>
<text id="15087">%null%</text>
<text id="15088">%null%</text>
<text id="15089">%null%</text>
<text id="15090">Можно добыть, охотясь на черепах</text>
<text id="15091">%null%</text>
<text id="15092">%null%</text>
<text id="15093">%null%</text>
<text id="15094">%null%</text>
<text id="15095">%null%</text>
<text id="15096">%null%</text>
<text id="15097">%null%</text>
<text id="15098">%null%</text>
<text id="15099">%null%</text>
<text id="15100">Можно добыть, охотясь на живых покойников</text>
<text id="15101">%null%</text>
<text id="15102">%null%</text>
<text id="15103">%null%</text>
<text id="15104">%null%</text>
<text id="15105">%null%</text>
<text id="15106">%null%</text>
<text id="15107">%null%</text>
<text id="15108">%null%</text>
<text id="15109">%null%</text>
<text id="15110">Можно добыть, охотясь на крупных стрекоз</text>
<text id="15111">%null%</text>
<text id="15112">%null%</text>
<text id="15113">%null%</text>
<text id="15114">%null%</text>
<text id="15115">%null%</text>
<text id="15116">%null%</text>
<text id="15117">%null%</text>
<text id="15118">%null%</text>
<text id="15119">%null%</text>
<text id="15120">Можно добыть, охотясь на сов</text>
<text id="15121">%null%</text>
<text id="15122">%null%</text>
<text id="15123">%null%</text>
<text id="15124">%null%</text>
<text id="15125">%null%</text>
<text id="15126">%null%</text>
<text id="15127">%null%</text>
<text id="15128">%null%</text>
<text id="15129">%null%</text>
<text id="15130">Можно добыть, охотясь на крупных крабов</text>
<text id="15131">%null%</text>
<text id="15132">%null%</text>
<text id="15133">%null%</text>
<text id="15134">%null%</text>
<text id="15135">%null%</text>
<text id="15136">%null%</text>
<text id="15137">%null%</text>
<text id="15138">%null%</text>
<text id="15139">%null%</text>
<text id="15140">Можно добыть, охотясь на наземных осьминогов</text>
<text id="15141">%null%</text>
<text id="15142">%null%</text>
<text id="15143">%null%</text>
<text id="15144">%null%</text>
<text id="15145">%null%</text>
<text id="15146">%null%</text>
<text id="15147">%null%</text>
<text id="15148">%null%</text>
<text id="15149">%null%</text>
<text id="15150">Можно добыть при убийстве цветков миранды</text>
<text id="15151">%null%</text>
<text id="15152">%null%</text>
<text id="15153">%null%</text>
<text id="15154">%null%</text>
<text id="15155">%null%</text>
<text id="15156">%null%</text>
<text id="15157">%null%</text>
<text id="15158">%null%</text>
<text id="15159">%null%</text>
<text id="15160">Можно добыть, охотясь на существ без крови</text>
<text id="15310">Часто встречается в лесах и зарослях</text>
<text id="15340">Можно добыть во время охоты на зверей</text>
<text id="15341">Можно добыть во время охоты на особо крупных зверей</text>
<text id="15390">Можно найти на обочине любой дороги</text>
<text id="15391">%null%</text>
<text id="15392">%null%</text>
<text id="15393">%null%</text>
<text id="15394">%null%</text>
<text id="15395">%null%</text>
<text id="15396">%null%</text>
<text id="15397">%null%</text>
<text id="15398">%null%</text>
<text id="15399">%null%</text>
<text id="15400">Часто носят с собой полулюди</text>
<text id="15401">%null%</text>
<text id="15402">%null%</text>
<text id="15403">%null%</text>
<text id="15404">%null%</text>
<text id="15405">%null%</text>
<text id="15406">%null%</text>
<text id="15407">%null%</text>
<text id="15408">%null%</text>
<text id="15409">%null%</text>
<text id="15410">Можно добыть при убийстве живых кувшинов</text>
<text id="15411">%null%</text>
<text id="15412">%null%</text>
<text id="15413">%null%</text>
<text id="15414">%null%</text>
<text id="15415">%null%</text>
<text id="15416">%null%</text>
<text id="15417">%null%</text>
<text id="15418">%null%</text>
<text id="15419">%null%</text>
<text id="15420">Можно добыть при убийстве альбиноров</text>
<text id="15421">%null%</text>
<text id="15422">%null%</text>
<text id="15423">%null%</text>
<text id="15424">%null%</text>
<text id="15425">%null%</text>
<text id="15426">%null%</text>
<text id="15427">%null%</text>
<text id="15428">%null%</text>
<text id="15429">%null%</text>
<text id="15430">Можно добыть при убийстве штормовых ястребов</text>
<text id="20650">Цветёт на отравленной земле</text>
<text id="20651">Встречается крайне редко</text>
<text id="20652">Цветёт в местах удара молнии</text>
<text id="20653">Встречается крайне редко</text>
<text id="20654">Цветёт на кладбищах</text>
<text id="20655">%null%</text>
<text id="20656">%null%</text>
<text id="20657">%null%</text>
<text id="20658">%null%</text>
<text id="20659">%null%</text>
<text id="20660">Цветёт на поражённой гнилью почве</text>
<text id="20680">Встречается повсеместно в Междуземье</text>
<text id="20681">Цветёт на плато Альтус</text>
<text id="20682">Цветёт на Вершинах великанов</text>
<text id="20683">Можно найти возле малых Древ Эрд</text>
<text id="20684">%null%</text>
<text id="20685">Можно найти возле малых Древ Эрд</text>
<text id="20686">%null%</text>
<text id="20687">%null%</text>
<text id="20688">%null%</text>
<text id="20689">%null%</text>
<text id="20690">Встречается в зарослях и других местах</text>
<text id="20691">Встречается крайне редко</text>
<text id="20710">Можно найти в Вечном городе и его окрестностях</text>
<text id="20711">%null%</text>
<text id="20712">%null%</text>
<text id="20713">%null%</text>
<text id="20714">%null%</text>
<text id="20715">%null%</text>
<text id="20716">%null%</text>
<text id="20717">%null%</text>
<text id="20718">%null%</text>
<text id="20719">%null%</text>
<text id="20720">Встречается по всему Междуземью</text>
<text id="20721">Можно без труда найти у Древа Эрд</text>
<text id="20722">Можно найти в холодных горных землях</text>
<text id="20723">Цветёт в пропитанной кровью земле</text>
<text id="20740">Растёт в землях, поражённых Пламенем Ярости</text>
<text id="20741">%null%</text>
<text id="20742">%null%</text>
<text id="20743">%null%</text>
<text id="20744">%null%</text>
<text id="20745">%null%</text>
<text id="20746">%null%</text>
<text id="20747">%null%</text>
<text id="20748">%null%</text>
<text id="20749">%null%</text>
<text id="20750">Можно запросто найти на озере Лиурнии</text>
<text id="20751">Можно запросто найти в холодных краях</text>
<text id="20752">%null%</text>
<text id="20753">Встречается крайне редко</text>
<text id="20754">%null%</text>
<text id="20755">%null%</text>
<text id="20756">%null%</text>
<text id="20757">%null%</text>
<text id="20758">%null%</text>
<text id="20759">%null%</text>
<text id="20760">Растёт во влажных зарослях и в других местах</text>
<text id="20761">Можно найти в Вечном городе и его окрестностях</text>
<text id="20762">%null%</text>
<text id="20763">%null%</text>
<text id="20764">%null%</text>
<text id="20765">%null%</text>
<text id="20766">%null%</text>
<text id="20767">%null%</text>
<text id="20768">%null%</text>
<text id="20769">%null%</text>
<text id="20770">Растёт на поражённой гнилью почве</text>
<text id="20771">%null%</text>
<text id="20772">%null%</text>
<text id="20773">%null%</text>
<text id="20774">%null%</text>
<text id="20775">Произрастает на корнях Великого древа.
На поверхности встречается близ деревьев.</text>
<text id="20776">%null%</text>
<text id="20777">%null%</text>
<text id="20778">%null%</text>
<text id="20779">%null%</text>
<text id="20780">Можно без труда найти в кристальных туннелях</text>
<text id="20795">Изредка можно найти возле упавших обломков</text>
<text id="20796">%null%</text>
<text id="20797">%null%</text>
<text id="20798">%null%</text>
<text id="20799">%null%</text>
<text id="20800">Встречается крайне редко</text>
<text id="20801">Можно найти в болоте Эония</text>
<text id="20802">Встречается в местах пожаров и не только</text>
<text id="20803">%null%</text>
<text id="20804">%null%</text>
<text id="20805">%null%</text>
<text id="20806">%null%</text>
<text id="20807">%null%</text>
<text id="20808">%null%</text>
<text id="20809">%null%</text>
<text id="20810">Можно найти на берегах холодных водоёмов, скрытых от солнечных лучей</text>
<text id="20811">Можно найти на берегах водоёмов у подножия малых Древ Эрд</text>
<text id="20812">Можно без труда найти на озере Лиурнии</text>
<text id="20813">%null%</text>
<text id="20814">%null%</text>
<text id="20815">%null%</text>
<text id="20816">%null%</text>
<text id="20817">%null%</text>
<text id="20818">%null%</text>
<text id="20819">%null%</text>
<text id="20820">Можно найти близ храмов и похожих построек</text>
<text id="20821">%null%</text>
<text id="20822">%null%</text>
<text id="20823">%null%</text>
<text id="20824">%null%</text>
<text id="20825">Можно найти в Вечном городе и его окрестностях</text>
<text id="20826">%null%</text>
<text id="20827">%null%</text>
<text id="20828">%null%</text>
<text id="20829">%null%</text>
<text id="20830">Часто попадаются в лесах и зарослях</text>
<text id="20831">Встречается в землях новой династии</text>
<text id="20832">%null%</text>
<text id="20833">%null%</text>
<text id="20834">%null%</text>
<text id="20835">%null%</text>
<text id="20836">%null%</text>
<text id="20837">%null%</text>
<text id="20838">%null%</text>
<text id="20839">%null%</text>
<text id="20840">Излучает бледный свет в тёмных пещерах</text>
<text id="20841">Излучает бледный свет в тёмных пещерах</text>
<text id="20842">Излучает бледный свет в тёмных пещерах</text>
<text id="20843">%null%</text>
<text id="20844">%null%</text>
<text id="20845">Можно найти в землях, поражённых Пламенем Ярости</text>
<text id="20846">%null%</text>
<text id="20847">%null%</text>
<text id="20848">%null%</text>
<text id="20849">%null%</text>
<text id="20850">Можно найти на вулкане Гельмир</text>
<text id="20851">%null%</text>
<text id="20852">Можно найти у реки Ансель и в других местах обитания огромных муравьёв</text>
<text id="20853">%null%</text>
<text id="20854">%null%</text>
<text id="20855">Можно найти в землях, некогда захваченных древними драконами</text>
<text id="200000">Тихея, Чёрный нож</text>
<text id="200001">Тихея, Чёрный нож</text>
<text id="200002">Тихея, Чёрный нож</text>
<text id="200003">Тихея, Чёрный нож</text>
<text id="200004">Тихея, Чёрный нож</text>
<text id="200005">Тихея, Чёрный нож</text>
<text id="200006">Тихея, Чёрный нож</text>
<text id="200007">Тихея, Чёрный нож</text>
<text id="200008">Тихея, Чёрный нож</text>
<text id="200009">Тихея, Чёрный нож</text>
<text id="200010">Тихея, Чёрный нож</text>
<text id="201000">Олег, рыцарь-изгнанник</text>
<text id="201001">Олег, рыцарь-изгнанник</text>
<text id="201002">Олег, рыцарь-изгнанник</text>
<text id="201003">Олег, рыцарь-изгнанник</text>
<text id="201004">Олег, рыцарь-изгнанник</text>
<text id="201005">Олег, рыцарь-изгнанник</text>
<text id="201006">Олег, рыцарь-изгнанник</text>
<text id="201007">Олег, рыцарь-изгнанник</text>
<text id="201008">Олег, рыцарь-изгнанник</text>
<text id="201009">Олег, рыцарь-изгнанник</text>
<text id="201010">Олег, рыцарь-изгнанник</text>
<text id="202000">Энгвол, рыцарь-изгнанник</text>
<text id="202001">Энгвол, рыцарь-изгнанник</text>
<text id="202002">Энгвол, рыцарь-изгнанник</text>
<text id="202003">Энгвол, рыцарь-изгнанник</text>
<text id="202004">Энгвол, рыцарь-изгнанник</text>
<text id="202005">Энгвол, рыцарь-изгнанник</text>
<text id="202006">Энгвол, рыцарь-изгнанник</text>
<text id="202007">Энгвол, рыцарь-изгнанник</text>
<text id="202008">Энгвол, рыцарь-изгнанник</text>
<text id="202009">Энгвол, рыцарь-изгнанник</text>
<text id="202010">Энгвол, рыцарь-изгнанник</text>
<text id="203000">Клыкастые бесы</text>
<text id="203001">Клыкастые бесы</text>
<text id="203002">Клыкастые бесы</text>
<text id="203003">Клыкастые бесы</text>
<text id="203004">Клыкастые бесы</text>
<text id="203005">Клыкастые бесы</text>
<text id="203006">Клыкастые бесы</text>
<text id="203007">Клыкастые бесы</text>
<text id="203008">Клыкастые бесы</text>
<text id="203009">Клыкастые бесы</text>
<text id="203010">Клыкастые бесы</text>
<text id="204000">Латенна, альбинорка</text>
<text id="204001">Латенна, альбинорка</text>
<text id="204002">Латенна, альбинорка</text>
<text id="204003">Латенна, альбинорка</text>
<text id="204004">Латенна, альбинорка</text>
<text id="204005">Латенна, альбинорка</text>
<text id="204006">Латенна, альбинорка</text>
<text id="204007">Латенна, альбинорка</text>
<text id="204008">Латенна, альбинорка</text>
<text id="204009">Латенна, альбинорка</text>
<text id="204010">Латенна, альбинорка</text>
<text id="205000">Кочевник</text>
<text id="205001">Кочевник</text>
<text id="205002">Кочевник</text>
<text id="205003">Кочевник</text>
<text id="205004">Кочевник</text>
<text id="205005">Кочевник</text>
<text id="205006">Кочевник</text>
<text id="205007">Кочевник</text>
<text id="205008">Кочевник</text>
<text id="205009">Кочевник</text>
<text id="205010">Кочевник</text>
<text id="206000">Ночная служанка и мечница</text>
<text id="206001">Ночная служанка и мечница</text>
<text id="206002">Ночная служанка и мечница</text>
<text id="206003">Ночная служанка и мечница</text>
<text id="206004">Ночная служанка и мечница</text>
<text id="206005">Ночная служанка и мечница</text>
<text id="206006">Ночная служанка и мечница</text>
<text id="206007">Ночная служанка и мечница</text>
<text id="206008">Ночная служанка и мечница</text>
<text id="206009">Ночная служанка и мечница</text>
<text id="206010">Ночная служанка и мечница</text>
<text id="207000">Ложная Слеза</text>
<text id="207001">Ложная Слеза</text>
<text id="207002">Ложная Слеза</text>
<text id="207003">Ложная Слеза</text>
<text id="207004">Ложная Слеза</text>
<text id="207005">Ложная Слеза</text>
<text id="207006">Ложная Слеза</text>
<text id="207007">Ложная Слеза</text>
<text id="207008">Ложная Слеза</text>
<text id="207009">Ложная Слеза</text>
<text id="207010">Ложная Слеза</text>
<text id="208000">Кристалиец</text>
<text id="208001">Кристалиец</text>
<text id="208002">Кристалиец</text>
<text id="208003">Кристалиец</text>
<text id="208004">Кристалиец</text>
<text id="208005">Кристалиец</text>
<text id="208006">Кристалиец</text>
<text id="208007">Кристалиец</text>
<text id="208008">Кристалиец</text>
<text id="208009">Кристалиец</text>
<text id="208010">Кристалиец</text>
<text id="209000">Почитатель предков</text>
<text id="209001">Почитатель предков</text>
<text id="209002">Почитатель предков</text>
<text id="209003">Почитатель предков</text>
<text id="209004">Почитатель предков</text>
<text id="209005">Почитатель предков</text>
<text id="209006">Почитатель предков</text>
<text id="209007">Почитатель предков</text>
<text id="209008">Почитатель предков</text>
<text id="209009">Почитатель предков</text>
<text id="209010">Почитатель предков</text>
<text id="210000">Крылатый бастард</text>
<text id="210001">Крылатый бастард</text>
<text id="210002">Крылатый бастард</text>
<text id="210003">Крылатый бастард</text>
<text id="210004">Крылатый бастард</text>
<text id="210005">Крылатый бастард</text>
<text id="210006">Крылатый бастард</text>
<text id="210007">Крылатый бастард</text>
<text id="210008">Крылатый бастард</text>
<text id="210009">Крылатый бастард</text>
<text id="210010">Крылатый бастард</text>
<text id="211000">Альбиноры</text>
<text id="211001">Альбиноры</text>
<text id="211002">Альбиноры</text>
<text id="211003">Альбиноры</text>
<text id="211004">Альбиноры</text>
<text id="211005">Альбиноры</text>
<text id="211006">Альбиноры</text>
<text id="211007">Альбиноры</text>
<text id="211008">Альбиноры</text>
<text id="211009">Альбиноры</text>
<text id="211010">Альбиноры</text>
<text id="212000">Скелеты-ополченцы</text>
<text id="212001">Скелеты-ополченцы</text>
<text id="212002">Скелеты-ополченцы</text>
<text id="212003">Скелеты-ополченцы</text>
<text id="212004">Скелеты-ополченцы</text>
<text id="212005">Скелеты-ополченцы</text>
<text id="212006">Скелеты-ополченцы</text>
<text id="212007">Скелеты-ополченцы</text>
<text id="212008">Скелеты-ополченцы</text>
<text id="212009">Скелеты-ополченцы</text>
<text id="212010">Скелеты-ополченцы</text>
<text id="213000">Скелет-разбойник</text>
<text id="213001">Скелет-разбойник</text>
<text id="213002">Скелет-разбойник</text>
<text id="213003">Скелет-разбойник</text>
<text id="213004">Скелет-разбойник</text>
<text id="213005">Скелет-разбойник</text>
<text id="213006">Скелет-разбойник</text>
<text id="213007">Скелет-разбойник</text>
<text id="213008">Скелет-разбойник</text>
<text id="213009">Скелет-разбойник</text>
<text id="213010">Скелет-разбойник</text>
<text id="214000">Послацы оракула</text>
<text id="214001">Послацы оракула</text>
<text id="214002">Послацы оракула</text>
<text id="214003">Послацы оракула</text>
<text id="214004">Послацы оракула</text>
<text id="214005">Послацы оракула</text>
<text id="214006">Послацы оракула</text>
<text id="214007">Послацы оракула</text>
<text id="214008">Послацы оракула</text>
<text id="214009">Послацы оракула</text>
<text id="214010">Послацы оракула</text>
<text id="215000">Гниющие трупы</text>
<text id="215001">Гниющие трупы</text>
<text id="215002">Гниющие трупы</text>
<text id="215003">Гниющие трупы</text>
<text id="215004">Гниющие трупы</text>
<text id="215005">Гниющие трупы</text>
<text id="215006">Гниющие трупы</text>
<text id="215007">Гниющие трупы</text>
<text id="215008">Гниющие трупы</text>
<text id="215009">Гниющие трупы</text>
<text id="215010">Гниющие трупы</text>
<text id="216000">Кармаан, порочный парфюмер</text>
<text id="216001">Кармаан, порочный парфюмер</text>
<text id="216002">Кармаан, порочный парфюмер</text>
<text id="216003">Кармаан, порочный парфюмер</text>
<text id="216004">Кармаан, порочный парфюмер</text>
<text id="216005">Кармаан, порочный парфюмер</text>
<text id="216006">Кармаан, порочный парфюмер</text>
<text id="216007">Кармаан, порочный парфюмер</text>
<text id="216008">Кармаан, порочный парфюмер</text>
<text id="216009">Кармаан, порочный парфюмер</text>
<text id="216010">Кармаан, порочный парфюмер</text>
<text id="217000">Парфюмерша Триша</text>
<text id="217001">Парфюмерша Триша</text>
<text id="217002">Парфюмерша Триша</text>
<text id="217003">Парфюмерша Триша</text>
<text id="217004">Парфюмерша Триша</text>
<text id="217005">Парфюмерша Триша</text>
<text id="217006">Парфюмерша Триша</text>
<text id="217007">Парфюмерша Триша</text>
<text id="217008">Парфюмерша Триша</text>
<text id="217009">Парфюмерша Триша</text>
<text id="217010">Парфюмерша Триша</text>
<text id="218000">Маг блестящих камней</text>
<text id="218001">Маг блестящих камней</text>
<text id="218002">Маг блестящих камней</text>
<text id="218003">Маг блестящих камней</text>
<text id="218004">Маг блестящих камней</text>
<text id="218005">Маг блестящих камней</text>
<text id="218006">Маг блестящих камней</text>
<text id="218007">Маг блестящих камней</text>
<text id="218008">Маг блестящих камней</text>
<text id="218009">Маг блестящих камней</text>
<text id="218010">Маг блестящих камней</text>
<text id="219000">Маг Двойной мудрости</text>
<text id="219001">Маг Двойной мудрости</text>
<text id="219002">Маг Двойной мудрости</text>
<text id="219003">Маг Двойной мудрости</text>
<text id="219004">Маг Двойной мудрости</text>
<text id="219005">Маг Двойной мудрости</text>
<text id="219006">Маг Двойной мудрости</text>
<text id="219007">Маг Двойной мудрости</text>
<text id="219008">Маг Двойной мудрости</text>
<text id="219009">Маг Двойной мудрости</text>
<text id="219010">Маг Двойной мудрости</text>
<text id="220000">Паж</text>
<text id="220001">Паж</text>
<text id="220002">Паж</text>
<text id="220003">Паж</text>
<text id="220004">Паж</text>
<text id="220005">Паж</text>
<text id="220006">Паж</text>
<text id="220007">Паж</text>
<text id="220008">Паж</text>
<text id="220009">Паж</text>
<text id="220010">Паж</text>
<text id="221000">Гуго, боевой маг</text>
<text id="221001">Гуго, боевой маг</text>
<text id="221002">Гуго, боевой маг</text>
<text id="221003">Гуго, боевой маг</text>
<text id="221004">Гуго, боевой маг</text>
<text id="221005">Гуго, боевой маг</text>
<text id="221006">Гуго, боевой маг</text>
<text id="221007">Гуго, боевой маг</text>
<text id="221008">Гуго, боевой маг</text>
<text id="221009">Гуго, боевой маг</text>
<text id="221010">Гуго, боевой маг</text>
<text id="222000">Глиняные люди</text>
<text id="222001">Глиняные люди </text>
<text id="222002">Глиняные люди </text>
<text id="222003">Глиняные люди</text>
<text id="222004">Глиняные люди </text>
<text id="222005">Глиняные люди </text>
<text id="222006">Глиняные люди</text>
<text id="222007">Глиняные люди </text>
<text id="222008">Глиняные люди </text>
<text id="222009">Глиняные люди</text>
<text id="222010">Глиняные люди </text>
<text id="223000">Финли, рыцарь чистой гнили</text>
<text id="223001">Финли, рыцарь чистой гнили</text>
<text id="223002">Финли, рыцарь чистой гнили</text>
<text id="223003">Финли, рыцарь чистой гнили</text>
<text id="223004">Финли, рыцарь чистой гнили</text>
<text id="223005">Финли, рыцарь чистой гнили</text>
<text id="223006">Финли, рыцарь чистой гнили</text>
<text id="223007">Финли, рыцарь чистой гнили</text>
<text id="223008">Финли, рыцарь чистой гнили</text>
<text id="223009">Финли, рыцарь чистой гнили</text>
<text id="223010">Финли, рыцарь чистой гнили</text>
<text id="224000">Родичи гнили</text>
<text id="224001">Родичи гнили</text>
<text id="224002">Родичи гнили</text>
<text id="224003">Родичи гнили</text>
<text id="224004">Родичи гнили</text>
<text id="224005">Родичи гнили</text>
<text id="224006">Родичи гнили</text>
<text id="224007">Родичи гнили</text>
<text id="224008">Родичи гнили</text>
<text id="224009">Родичи гнили</text>
<text id="224010">Родичи гнили</text>
<text id="225000">Солдаты-марионетки</text>
<text id="225001">Солдаты-марионетки</text>
<text id="225002">Солдаты-марионетки</text>
<text id="225003">Солдаты-марионетки</text>
<text id="225004">Солдаты-марионетки</text>
<text id="225005">Солдаты-марионетки</text>
<text id="225006">Солдаты-марионетки</text>
<text id="225007">Солдаты-марионетки</text>
<text id="225008">Солдаты-марионетки</text>
<text id="225009">Солдаты-марионетки</text>
<text id="225010">Солдаты-марионетки</text>
<text id="226000">Летающие марионетки</text>
<text id="226001">Летающие марионетки</text>
<text id="226002">Летающие марионетки</text>
<text id="226003">Летающие марионетки</text>
<text id="226004">Летающие марионетки</text>
<text id="226005">Летающие марионетки</text>
<text id="226006">Летающие марионетки</text>
<text id="226007">Летающие марионетки</text>
<text id="226008">Летающие марионетки</text>
<text id="226009">Летающие марионетки</text>
<text id="226010">Летающие марионетки</text>
<text id="227000">Огненный монах</text>
<text id="227001">Огненный монах</text>
<text id="227002">Огненный монах</text>
<text id="227003">Огненный монах</text>
<text id="227004">Огненный монах</text>
<text id="227005">Огненный монах</text>
<text id="227006">Огненный монах</text>
<text id="227007">Огненный монах</text>
<text id="227008">Огненный монах</text>
<text id="227009">Огненный монах</text>
<text id="227010">Огненный монах</text>
<text id="228000">Амон, монах чёрного пламени</text>
<text id="228001">Амон, монах чёрного пламени</text>
<text id="228002">Амон, монах чёрного пламени</text>
<text id="228003">Амон, монах чёрного пламени</text>
<text id="228004">Амон, монах чёрного пламени</text>
<text id="228005">Амон, монах чёрного пламени</text>
<text id="228006">Амон, монах чёрного пламени</text>
<text id="228007">Амон, монах чёрного пламени</text>
<text id="228008">Амон, монах чёрного пламени</text>
<text id="228009">Амон, монах чёрного пламени</text>
<text id="228010">Амон, монах чёрного пламени</text>
<text id="229000">Змеелюд</text>
<text id="229001">Змеелюд</text>
<text id="229002">Змеелюд</text>
<text id="229003">Змеелюд</text>
<text id="229004">Змеелюд</text>
<text id="229005">Змеелюд</text>
<text id="229006">Змеелюд</text>
<text id="229007">Змеелюд</text>
<text id="229008">Змеелюд</text>
<text id="229009">Змеелюд</text>
<text id="229010">Змеелюд</text>
<text id="230000">Зверолюди из Азулы</text>
<text id="230001">Зверолюди из Азулы</text>
<text id="230002">Зверолюди из Азулы</text>
<text id="230003">Зверолюди из Азулы</text>
<text id="230004">Зверолюди из Азулы</text>
<text id="230005">Зверолюди из Азулы</text>
<text id="230006">Зверолюди из Азулы</text>
<text id="230007">Зверолюди из Азулы</text>
<text id="230008">Зверолюди из Азулы</text>
<text id="230009">Зверолюди из Азулы</text>
<text id="230010">Зверолюди из Азулы</text>
<text id="231000">Наёмник из Кайдена</text>
<text id="231001">Наёмник из Кайдена</text>
<text id="231002">Наёмник из Кайдена</text>
<text id="231003">Наёмник из Кайдена</text>
<text id="231004">Наёмник из Кайдена</text>
<text id="231005">Наёмник из Кайдена</text>
<text id="231006">Наёмник из Кайдена</text>
<text id="231007">Наёмник из Кайдена</text>
<text id="231008">Наёмник из Кайдена</text>
<text id="231009">Наёмник из Кайдена</text>
<text id="231010">Наёмник из Кайдена</text>
<text id="232000">Волки-одиночки</text>
<text id="232001">Волки-одиночки</text>
<text id="232002">Волки-одиночки</text>
<text id="232003">Волки-одиночки</text>
<text id="232004">Волки-одиночки</text>
<text id="232005">Волки-одиночки</text>
<text id="232006">Волки-одиночки</text>
<text id="232007">Волки-одиночки</text>
<text id="232008">Волки-одиночки</text>
<text id="232009">Волки-одиночки</text>
<text id="232010">Волки-одиночки</text>
<text id="233000">Гигантские крысы</text>
<text id="233001">Гигантские крысы</text>
<text id="233002">Гигантские крысы</text>
<text id="233003">Гигантские крысы</text>
<text id="233004">Гигантские крысы</text>
<text id="233005">Гигантские крысы</text>
<text id="233006">Гигантские крысы</text>
<text id="233007">Гигантские крысы</text>
<text id="233008">Гигантские крысы</text>
<text id="233009">Гигантские крысы</text>
<text id="233010">Гигантские крысы</text>
<text id="234000">Полулюди</text>
<text id="234001">Полулюди</text>
<text id="234002">Полулюди</text>
<text id="234003">Полулюди</text>
<text id="234004">Полулюди</text>
<text id="234005">Полулюди</text>
<text id="234006">Полулюди</text>
<text id="234007">Полулюди</text>
<text id="234008">Полулюди</text>
<text id="234009">Полулюди</text>
<text id="234010">Полулюди</text>
<text id="235000">Гниющий бродячий пёс</text>
<text id="235001">Гниющий бродячий пёс</text>
<text id="235002">Гниющий бродячий пёс</text>
<text id="235003">Гниющий бродячий пёс</text>
<text id="235004">Гниющий бродячий пёс</text>
<text id="235005">Гниющий бродячий пёс</text>
<text id="235006">Гниющий бродячий пёс</text>
<text id="235007">Гниющий бродячий пёс</text>
<text id="235008">Гниющий бродячий пёс</text>
<text id="235009">Гниющий бродячий пёс</text>
<text id="235010">Гниющий бродячий пёс</text>
<text id="236000">Призрачная медуза</text>
<text id="236001">Призрачная медуза</text>
<text id="236002">Призрачная медуза</text>
<text id="236003">Призрачная медуза</text>
<text id="236004">Призрачная медуза</text>
<text id="236005">Призрачная медуза</text>
<text id="236006">Призрачная медуза</text>
<text id="236007">Призрачная медуза</text>
<text id="236008">Призрачная медуза</text>
<text id="236009">Призрачная медуза</text>
<text id="236010">Призрачная медуза</text>
<text id="237000">Боевой ястреб</text>
<text id="237001">Боевой ястреб</text>
<text id="237002">Боевой ястреб</text>
<text id="237003">Боевой ястреб</text>
<text id="237004">Боевой ястреб</text>
<text id="237005">Боевой ястреб</text>
<text id="237006">Боевой ястреб</text>
<text id="237007">Боевой ястреб</text>
<text id="237008">Боевой ястреб</text>
<text id="237009">Боевой ястреб</text>
<text id="237010">Боевой ястреб</text>
<text id="238000">Штормовой ястреб Дин</text>
<text id="238001">Штормовой ястреб Дин</text>
<text id="238002">Штормовой ястреб Дин</text>
<text id="238003">Штормовой ястреб Дин</text>
<text id="238004">Штормовой ястреб Дин</text>
<text id="238005">Штормовой ястреб Дин</text>
<text id="238006">Штормовой ястреб Дин</text>
<text id="238007">Штормовой ястреб Дин</text>
<text id="238008">Штормовой ястреб Дин</text>
<text id="238009">Штормовой ястреб Дин</text>
<text id="238010">Штормовой ястреб Дин</text>
<text id="239000">Флоу, рыцарь-ищейка</text>
<text id="239001">Флоу, рыцарь-ищейка</text>
<text id="239002">Флоу, рыцарь-ищейка</text>
<text id="239003">Флоу, рыцарь-ищейка</text>
<text id="239004">Флоу, рыцарь-ищейка</text>
<text id="239005">Флоу, рыцарь-ищейка</text>
<text id="239006">Флоу, рыцарь-ищейка</text>
<text id="239007">Флоу, рыцарь-ищейка</text>
<text id="239008">Флоу, рыцарь-ищейка</text>
<text id="239009">Флоу, рыцарь-ищейка</text>
<text id="239010">Флоу, рыцарь-ищейка</text>
<text id="240000">Странствующие вельможи</text>
<text id="240001">Странствующие вельможи</text>
<text id="240002">Странствующие вельможи</text>
<text id="240003">Странствующие вельможи</text>
<text id="240004">Странствующие вельможи</text>
<text id="240005">Странствующие вельможи</text>
<text id="240006">Странствующие вельможи</text>
<text id="240007">Странствующие вельможи</text>
<text id="240008">Странствующие вельможи</text>
<text id="240009">Странствующие вельможи</text>
<text id="240010">Странствующие вельможи</text>
<text id="241000">Высокородный чародей</text>
<text id="241001">Высокородный чародей</text>
<text id="241002">Высокородный чародей</text>
<text id="241003">Высокородный чародей</text>
<text id="241004">Высокородный чародей</text>
<text id="241005">Высокородный чародей</text>
<text id="241006">Высокородный чародей</text>
<text id="241007">Высокородный чародей</text>
<text id="241008">Высокородный чародей</text>
<text id="241009">Высокородный чародей</text>
<text id="241010">Высокородный чародей</text>
<text id="242000">Плебеи-ополченцы</text>
<text id="242001">Плебеи-ополченцы</text>
<text id="242002">Плебеи-ополченцы</text>
<text id="242003">Плебеи-ополченцы</text>
<text id="242004">Плебеи-ополченцы</text>
<text id="242005">Плебеи-ополченцы</text>
<text id="242006">Плебеи-ополченцы</text>
<text id="242007">Плебеи-ополченцы</text>
<text id="242008">Плебеи-ополченцы</text>
<text id="242009">Плебеи-ополченцы</text>
<text id="242010">Плебеи-ополченцы</text>
<text id="243000">Тыквоголовый безумец</text>
<text id="243001">Тыквоголовый безумец</text>
<text id="243002">Тыквоголовый безумец</text>
<text id="243003">Тыквоголовый безумец</text>
<text id="243004">Тыквоголовый безумец</text>
<text id="243005">Тыквоголовый безумец</text>
<text id="243006">Тыквоголовый безумец</text>
<text id="243007">Тыквоголовый безумец</text>
<text id="243008">Тыквоголовый безумец</text>
<text id="243009">Тыквоголовый безумец</text>
<text id="243010">Тыквоголовый безумец</text>
<text id="244000">Земляные брызгуны</text>
<text id="244001">Земляные брызгуны</text>
<text id="244002">Земляные брызгуны</text>
<text id="244003">Земляные брызгуны</text>
<text id="244004">Земляные брызгуны</text>
<text id="244005">Земляные брызгуны</text>
<text id="244006">Земляные брызгуны</text>
<text id="244007">Земляные брызгуны</text>
<text id="244008">Земляные брызгуны</text>
<text id="244009">Земляные брызгуны</text>
<text id="244010">Земляные брызгуны</text>
<text id="245000">Цветки миранды</text>
<text id="245001">Цветки миранды</text>
<text id="245002">Цветки миранды</text>
<text id="245003">Цветки миранды</text>
<text id="245004">Цветки миранды</text>
<text id="245005">Цветки миранды</text>
<text id="245006">Цветки миранды</text>
<text id="245007">Цветки миранды</text>
<text id="245008">Цветки миранды</text>
<text id="245009">Цветки миранды</text>
<text id="245010">Цветки миранды</text>
<text id="246000">Солдаты удачи</text>
<text id="246001">Солдаты удачи</text>
<text id="246002">Солдаты удачи</text>
<text id="246003">Солдаты удачи</text>
<text id="246004">Солдаты удачи</text>
<text id="246005">Солдаты удачи</text>
<text id="246006">Солдаты удачи</text>
<text id="246007">Солдаты удачи</text>
<text id="246008">Солдаты удачи</text>
<text id="246009">Солдаты удачи</text>
<text id="246010">Солдаты удачи</text>
<text id="247000">Убийца знамений Ролло</text>
<text id="247001">Убийца знамений Ролло</text>
<text id="247002">Убийца знамений Ролло</text>
<text id="247003">Убийца знамений Ролло</text>
<text id="247004">Убийца знамений Ролло</text>
<text id="247005">Убийца знамений Ролло</text>
<text id="247006">Убийца знамений Ролло</text>
<text id="247007">Убийца знамений Ролло</text>
<text id="247008">Убийца знамений Ролло</text>
<text id="247009">Убийца знамений Ролло</text>
<text id="247010">Убийца знамений Ролло</text>
<text id="248000">Солдаты с большими щитами</text>
<text id="248001">Солдаты с большими щитами</text>
<text id="248002">Солдаты с большими щитами</text>
<text id="248003">Солдаты с большими щитами</text>
<text id="248004">Солдаты с большими щитами</text>
<text id="248005">Солдаты с большими щитами</text>
<text id="248006">Солдаты с большими щитами</text>
<text id="248007">Солдаты с большими щитами</text>
<text id="248008">Солдаты с большими щитами</text>
<text id="248009">Солдаты с большими щитами</text>
<text id="248010">Солдаты с большими щитами</text>
<text id="249000">Лучники</text>
<text id="249001">Лучники</text>
<text id="249002">Лучники</text>
<text id="249003">Лучники</text>
<text id="249004">Лучники</text>
<text id="249005">Лучники</text>
<text id="249006">Лучники</text>
<text id="249007">Лучники</text>
<text id="249008">Лучники</text>
<text id="249009">Лучники</text>
<text id="249010">Лучники</text>
<text id="250000">Солдаты Годрика</text>
<text id="250001">Солдаты Годрика</text>
<text id="250002">Солдаты Годрика</text>
<text id="250003">Солдаты Годрика</text>
<text id="250004">Солдаты Годрика</text>
<text id="250005">Солдаты Годрика</text>
<text id="250006">Солдаты Годрика</text>
<text id="250007">Солдаты Годрика</text>
<text id="250008">Солдаты Годрика</text>
<text id="250009">Солдаты Годрика</text>
<text id="250010">Солдаты Годрика</text>
<text id="251000">Солдаты Райи Лукарии</text>
<text id="251001">Солдаты Райи Лукарии</text>
<text id="251002">Солдаты Райи Лукарии</text>
<text id="251003">Солдаты Райи Лукарии</text>
<text id="251004">Солдаты Райи Лукарии</text>
<text id="251005">Солдаты Райи Лукарии</text>
<text id="251006">Солдаты Райи Лукарии</text>
<text id="251007">Солдаты Райи Лукарии</text>
<text id="251008">Солдаты Райи Лукарии</text>
<text id="251009">Солдаты Райи Лукарии</text>
<text id="251010">Солдаты Райи Лукарии</text>
<text id="252000">Солдаты Лейнделла</text>
<text id="252001">Солдаты Лейнделла</text>
<text id="252002">Солдаты Лейнделла</text>
<text id="252003">Солдаты Лейнделла</text>
<text id="252004">Солдаты Лейнделла</text>
<text id="252005">Солдаты Лейнделла</text>
<text id="252006">Солдаты Лейнделла</text>
<text id="252007">Солдаты Лейнделла</text>
<text id="252008">Солдаты Лейнделла</text>
<text id="252009">Солдаты Лейнделла</text>
<text id="252010">Солдаты Лейнделла</text>
<text id="253000">Солдаты Радана</text>
<text id="253001">Солдаты Радана</text>
<text id="253002">Солдаты Радана</text>
<text id="253003">Солдаты Радана</text>
<text id="253004">Солдаты Радана</text>
<text id="253005">Солдаты Радана</text>
<text id="253006">Солдаты Радана</text>
<text id="253007">Солдаты Радана</text>
<text id="253008">Солдаты Радана</text>
<text id="253009">Солдаты Радана</text>
<text id="253010">Солдаты Радана</text>
<text id="254000">Солдаты мавзолея</text>
<text id="254001">Солдаты мавзолея</text>
<text id="254002">Солдаты мавзолея</text>
<text id="254003">Солдаты мавзолея</text>
<text id="254004">Солдаты мавзолея</text>
<text id="254005">Солдаты мавзолея</text>
<text id="254006">Солдаты мавзолея</text>
<text id="254007">Солдаты мавзолея</text>
<text id="254008">Солдаты мавзолея</text>
<text id="254009">Солдаты мавзолея</text>
<text id="254010">Солдаты мавзолея</text>
<text id="255000">Солдаты Святого Древа</text>
<text id="255001">Солдаты Святого Древа</text>
<text id="255002">Солдаты Святого Древа</text>
<text id="255003">Солдаты Святого Древа</text>
<text id="255004">Солдаты Святого Древа</text>
<text id="255005">Солдаты Святого Древа</text>
<text id="255006">Солдаты Святого Древа</text>
<text id="255007">Солдаты Святого Древа</text>
<text id="255008">Солдаты Святого Древа</text>
<text id="255009">Солдаты Святого Древа</text>
<text id="255010">Солдаты Святого Древа</text>
<text id="256000">Кристофф, рыцарь древних драконов</text>
<text id="256001">Кристофф, рыцарь древних драконов</text>
<text id="256002">Кристофф, рыцарь древних драконов</text>
<text id="256003">Кристофф, рыцарь древних драконов</text>
<text id="256004">Кристофф, рыцарь древних драконов</text>
<text id="256005">Кристофф, рыцарь древних драконов</text>
<text id="256006">Кристофф, рыцарь древних драконов</text>
<text id="256007">Кристофф, рыцарь древних драконов</text>
<text id="256008">Кристофф, рыцарь древних драконов</text>
<text id="256009">Кристофф, рыцарь древних драконов</text>
<text id="256010">Кристофф, рыцарь древних драконов</text>
<text id="257000">Ога, рыцарь Рыжей Гривы</text>
<text id="257001">Ога, рыцарь Рыжей Гривы</text>
<text id="257002">Ога, рыцарь Рыжей Гривы</text>
<text id="257003">Ога, рыцарь Рыжей Гривы</text>
<text id="257004">Ога, рыцарь Рыжей Гривы</text>
<text id="257005">Ога, рыцарь Рыжей Гривы</text>
<text id="257006">Ога, рыцарь Рыжей Гривы</text>
<text id="257007">Ога, рыцарь Рыжей Гривы</text>
<text id="257008">Ога, рыцарь Рыжей Гривы</text>
<text id="257009">Ога, рыцарь Рыжей Гривы</text>
<text id="257010">Ога, рыцарь Рыжей Гривы</text>
<text id="258000">Лутель Безголовая</text>
<text id="258001">Лутель Безголовая</text>
<text id="258002">Лутель Безголовая</text>
<text id="258003">Лутель Безголовая</text>
<text id="258004">Лутель Безголовая</text>
<text id="258005">Лутель Безголовая</text>
<text id="258006">Лутель Безголовая</text>
<text id="258007">Лутель Безголовая</text>
<text id="258008">Лутель Безголовая</text>
<text id="258009">Лутель Безголовая</text>
<text id="258010">Лутель Безголовая</text>
<text id="259000">Нефели Лукс</text>
<text id="259001">Нефели Лукс</text>
<text id="259002">Нефели Лукс</text>
<text id="259003">Нефели Лукс</text>
<text id="259004">Нефели Лукс</text>
<text id="259005">Нефели Лукс</text>
<text id="259006">Нефели Лукс</text>
<text id="259007">Нефели Лукс</text>
<text id="259008">Нефели Лукс</text>
<text id="259009">Нефели Лукс</text>
<text id="259010">Нефели Лукс</text>
<text id="260000">Поедатель Отбросов</text>
<text id="260001">Поедатель Отбросов</text>
<text id="260002">Поедатель Отбросов</text>
<text id="260003">Поедатель Отбросов</text>
<text id="260004">Поедатель Отбросов</text>
<text id="260005">Поедатель Отбросов</text>
<text id="260006">Поедатель Отбросов</text>
<text id="260007">Поедатель Отбросов</text>
<text id="260008">Поедатель Отбросов</text>
<text id="260009">Поедатель Отбросов</text>
<text id="260010">Поедатель Отбросов</text>
<text id="261000">Теролина, служанка Пальца</text>
<text id="261001">Теролина, служанка Пальца</text>
<text id="261002">Теролина, служанка Пальца</text>
<text id="261003">Теролина, служанка Пальца</text>
<text id="261004">Теролина, служанка Пальца</text>
<text id="261005">Теролина, служанка Пальца</text>
<text id="261006">Теролина, служанка Пальца</text>
<text id="261007">Теролина, служанка Пальца</text>
<text id="261008">Теролина, служанка Пальца</text>
<text id="261009">Теролина, служанка Пальца</text>
<text id="261010">Теролина, служанка Пальца</text>
<text id="262000">Долорес Спящая Стрела</text>
<text id="262001">Долорес Спящая Стрела</text>
<text id="262002">Долорес Спящая Стрела</text>
<text id="262003">Долорес Спящая Стрела</text>
<text id="262004">Долорес Спящая Стрела</text>
<text id="262005">Долорес Спящая Стрела</text>
<text id="262006">Долорес Спящая Стрела</text>
<text id="262007">Долорес Спящая Стрела</text>
<text id="262008">Долорес Спящая Стрела</text>
<text id="262009">Долорес Спящая Стрела</text>
<text id="262010">Долорес Спящая Стрела</text>
<text id="263000">Метатель горшков</text>
<text id="263001">Метатель горшков</text>
<text id="263002">Метатель горшков</text>
<text id="263003">Метатель горшков</text>
<text id="263004">Метатель горшков</text>
<text id="263005">Метатель горшков</text>
<text id="263006">Метатель горшков</text>
<text id="263007">Метатель горшков</text>
<text id="263008">Метатель горшков</text>
<text id="263009">Метатель горшков</text>
<text id="263010">Метатель горшков</text>
</entries>
</fmg>